LICENSE
README.md
setup.cfg
setup.py
wininfparser.py
wininfparser.egg-info/PKG-INFO
wininfparser.egg-info/SOURCES.txt
wininfparser.egg-info/dependency_links.txt
wininfparser.egg-info/top_level.txt