Metadata-Version: 2.1
Name: wininfparser
Version: 1.0.12a0
Summary: INF file parser
Home-page: https://github.com/arutar/wininfparser
Author: Arsen Arutyunyan
Author-email: arutar@bk.ru
License: GPLv3
Keywords: inf parser,inf file parser,Windows INF parser
Platform: UNKNOWN
